redis_encdec/__init__.py
redis_encdec/redis_encoder_decoder.py
redis_encdec-0.1.1.dist-info/LICENSE
redis_encdec-0.1.1.dist-info/METADATA
redis_encdec-0.1.1.dist-info/WHEEL
redis_encdec-0.1.1.dist-info/RECORD
