Metadata-Version: 2.1
Name: redis-encdec
Version: 0.1.1
Summary: A utility module for encoding and decoding dictionaries with JSON values for use with Redis.
Home-page: https://github.com/carlinix/redis-encoder-decoder
License: LGPL-2.1
Keywords: redis,encoder,decoder,json,utility
Author: Ricardo Carlini
Author-email: rcarlini@gmail.com
Requires-Python: >=3.9,<4.0
Classifier: License :: OSI Approved
Classifier: Programming Language :: Python :: 3
Classifier: Programming Language :: Python :: 3.9
Classifier: Programming Language :: Python :: 3.10
Classifier: Programming Language :: Python :: 3.11
Classifier: Programming Language :: Python :: 3.12
Requires-Dist: redis (>=4.0.2,<5.0.0)
Project-URL: Repository, https://github.com/carlinix/redis-encoder-decoder
